setup.cfg
setup.py
csscolor/__init__.py
csscolor/color.py
csscolor/colors.py
csscolor/parse.py
csscolor.egg-info/PKG-INFO
csscolor.egg-info/SOURCES.txt
csscolor.egg-info/dependency_links.txt
csscolor.egg-info/not-zip-safe
csscolor.egg-info/top_level.txt