Metadata-Version: 1.1
Name: csscolor
Version: 0.5.1
Summary: CSS colors and parsing.
Home-page: http://github.com/idmillington/csscolor
Author: Ian Millington
Author-email: idmillington@googlemail.com
License: UNKNOWN
Download-URL: https://github.com/idmillington/csscolor/tarball/master
Keywords: csscolor,css,color,colour
Platform: UNKNOWN
Classifier: Programming Language :: Python :: 3
Classifier: Development Status :: 4 - Beta
Classifier: Environment :: Console
Classifier: Intended Audience :: Developers
Classifier: License :: OSI Approved :: MIT License
Classifier: Operating System :: OS Independent
Classifier: Topic :: Multimedia :: Graphics
